mux4x1_assign/mux4x1.v

/********************************************************************

Module          :   mux4x1

Date            :   10 November, 2022

Author          :   Krunal Gandhi

Email           :   gkrunal72@gmail.com

History         :   1. 10 November, 2022 - Initial implementation

Summary         :   Implementation of Mux4x1 using assign statements.
                    core logic is of mux4x1 using mux2x1.

Inputs          :   i0, i1, i2, i3, sel

Outputs         :   Out

Instantiation   :   N/A

********************************************************************/

module mux4x1 (
    input   wire        i0,
    input   wire        i1,
    input   wire        i2,
    input   wire        i3,
    input   wire  [1:0] sel,
    output  reg         out
    );

wire    m1;
wire    m2;

assign m1 = sel[0] ? i1 : i0;
assign m2 = sel[0] ? i3 : i2;
assign out = sel[1] ? m2 : m1;

endmodule

mux8x1/mux8x1.v

/********************************************************************

Module          :   mux8x1

Date            :   10 November, 2022

Author          :   Krunal Gandhi

Email           :   gkrunal72@gmail.com

History         :   1. 10 November, 2022 - Initial implementation

Summary         :   Implementation of Mux8x1 using mux4x1 only.
                    Instantiating mux4x1 to impletement mumx8x1.

Inputs          :   i0, i1, i2, i3, i4, i5, i6, i7, sel

Outputs         :   Out

Instantiation   :   mux4x1

********************************************************************/

`include "mux4x1.v"

module mux8x1 (
    input   wire        i0,
    input   wire        i1,
    input   wire        i2,
    input   wire        i3,
    input   wire        i4,
    input   wire        i5,
    input   wire        i6,
    input   wire        i7,
    input   wire [2:0]  sel,
    output  wire        out
);

wire    m1;
wire    m2;

mux4x1 mux1 (i0,
             i1,
             i2,
             i3,
             {sel[1],sel[0]},
             m1
         );

mux4x1 mux2 (i4,
             i5,
             i6,
             i7,
             {sel[1],sel[0]},
             m2
         );

         
mux4x1 mux3 (m1,
             m2,
             1'b0,
             1'b0,
             {1'b0, sel[2]},
             out
         );

endmodule

mux8x1/mux8x1_tb.v
/********************************************************************

Module          :   mux8x1_tb

Date            :   10 November, 2022

Author          :   Krunal Gandhi

Email           :   gkrunal72@gmail.com

History         :   1. 10 November, 2022 - Initial implementation

Summary         :   Test bench for mux8x1.v implemented using mux4x1 only

Inputs          :   i0_tb, i1_tb, i2_tb, i3_tb, i4_tb, i5_tb, i6_tb, i7_tb, sel_tb

Outputs         :   Out_tb

Instantiation   :   mux8x1

********************************************************************/

`include "mux8x1.v"
`include "mux4x1.v"

module mux8x1_tb;

reg         i0_tb;
reg         i1_tb;
reg         i2_tb;
reg         i3_tb;
reg         i4_tb;
reg         i5_tb;
reg         i6_tb;
reg         i7_tb;
reg  [2:0]  sel_tb;

wire        out_tb;

mux8x1 dut (.i0(i0_tb),
            .i1(i1_tb),
            .i2(i2_tb),
            .i3(i3_tb), 
            .i4(i4_tb), 
            .i5(i5_tb),
            .i6(i6_tb),
            .i7(i7_tb),
            .sel(sel_tb),
            .out(out_tb)
            );


initial begin

    repeat (10) begin
        i0_tb=$random;
        i1_tb=$random;
        i2_tb=$random;
        i3_tb=$random;
        i4_tb=$random;
        i5_tb=$random;
        i6_tb=$random;
        i7_tb=$random;
        sel_tb=$random;
        #1;
    end
end

initial begin
    $dumpfile("mux8x1.vcd");
    $dumpvars(0,mux8x1_tb);
end

initial begin
    $monitor("Time = %0t, I0 = %b, I1 = %b, I2 = %b, I3 = %b, I4 = %b, I5 = %b, I6 = %b, I7 = %b, SEL = %d, Out = %b", $time, i0_tb, i1_tb, i2_tb, i3_tb, i4_tb, i5_tb, i6_tb, i7_tb, sel_tb, out_tb);
end

endmodule

mux8x1/mux8x1.vcd
$date
	Mon Nov 14 17:42:50 2022
$end
$version
	ModelSim Version 2020.1
$end
$timescale
	1ps
$end

$scope module mux8x1_tb $end
$var reg 1 ! i0_tb $end
$var reg 1 " i1_tb $end
$var reg 1 # i2_tb $end
$var reg 1 $ i3_tb $end
$var reg 1 % i4_tb $end
$var reg 1 & i5_tb $end
$var reg 1 ' i6_tb $end
$var reg 1 ( i7_tb $end
$var reg 3 ) sel_tb [2:0] $end
$var wire 1 * out_tb $end

$scope module dut $end
$var wire 1 + i0 $end
$var wire 1 , i1 $end
$var wire 1 - i2 $end
$var wire 1 . i3 $end
$var wire 1 / i4 $end
$var wire 1 0 i5 $end
$var wire 1 1 i6 $end
$var wire 1 2 i7 $end
$var wire 1 3 sel [2] $end
$var wire 1 4 sel [1] $end
$var wire 1 5 sel [0] $end
$var wire 1 * out $end
$var wire 1 6 m1 $end
$var wire 1 7 m2 $end

$scope module mux1 $end
$var wire 1 + i0 $end
$var wire 1 , i1 $end
$var wire 1 - i2 $end
$var wire 1 . i3 $end
$var wire 1 4 sel [1] $end
$var wire 1 5 sel [0] $end
$var reg 1 8 out $end
$var wire 1 9 m1 $end
$var wire 1 : m2 $end
$upscope $end

$scope module mux2 $end
$var wire 1 / i0 $end
$var wire 1 0 i1 $end
$var wire 1 1 i2 $end
$var wire 1 2 i3 $end
$var wire 1 4 sel [1] $end
$var wire 1 5 sel [0] $end
$var reg 1 ; out $end
$var wire 1 < m1 $end
$var wire 1 = m2 $end
$upscope $end

$scope module mux3 $end
$var wire 1 6 i0 $end
$var wire 1 7 i1 $end
$var wire 1 > i2 $end
$var wire 1 ? i3 $end
$var wire 1 @ sel [1] $end
$var wire 1 3 sel [0] $end
$var reg 1 A out $end
$var wire 1 B m1 $end
$var wire 1 C m2 $end
$upscope $end
$upscope $end
$upscope $end
$enddefinitions $end
#0
$dumpvars
0!
1"
1#
1$
1%
1&
1'
0(
b1 )
18
1;
1A
1*
16
17
19
1:
1<
0=
1B
0C
15
04
03
02
11
10
1/
1.
1-
1,
0+
0@
0?
0>
$end
#1
1!
0"
0%
0'
1(
b10 )
1+
0,
0/
01
12
05
14
0<
0;
07
#2
1"
0#
0&
b100 )
1,
0-
00
04
13
0B
0:
0A
0*
#3
1#
0(
b101 )
1-
02
15
1:
#4
0!
1%
1&
0+
1/
10
1<
1;
17
1B
1A
1*
#5
1!
0#
0$
0%
0&
1(
b0 )
1+
0-
0.
0/
00
12
05
03
0<
0:
0;
07
#6
0!
1#
0(
b11 )
0+
1-
02
15
14
08
06
0B
0A
0*
#7
1!
1$
1'
1(
b1 )
1+
1.
11
12
04
1=
1:
18
16
1B
1A
1*
#8
0!
0"
1&
0(
b11 )
0+
0,
10
02
14
0=
1<
09
#9
1!
1"
0#
1%
0&
0'
b0 )
1+
1,
0-
1/
00
01
05
04
0:
19
1;
17
