mux2x1_gate_level/mux2x1.v
module mux2x1 (i0, i1, sel, y);

input i0, i1, sel;
output y;

wire isel, o1, o2;

not g1 (isel,sel);
and g2 (o1, isel, i0);
and g3 (o2, sel, i1);
or g4 (y, o1, o2);

endmodule

mux2x1_gate_level/mux2x1_tb.v
`include "mux2x1.v"         //Include DUT file to instantiate the modules

module mux2x1_tb;

reg i0_tb, i1_tb, sel_tb;   //Inputs to the DUT (Mux2x1.v)
wire y_tb;                  //Output of DUT

//Instantiation of module - Connection by name
mux2x1 m1 ( .i0(i0_tb), 
            .i1(i1_tb), 
            .sel(sel_tb), 
            .y(y_tb));

initial begin

//Execute the instructions "n" (e.g. 10) number of times
repeat (10) begin

    i0_tb = $random;        //$random - To assign random values
    i1_tb = $random;        //In our case 0 or 1 as our variable are of 1 bit
    sel_tb = $random;
    #1;
end    

end

initial begin
    //Print the value of variables continuously whenever value of variable changes
    $monitor("time - %0t, i0=%b, i1=%b, sel=%b, y=%b", $time, i0_tb, i1_tb, sel_tb, y_tb);
end

initial begin
    
    $dumpfile("mux.vcd"); //Value change dump file
    $dumpvars(0,mux2x1_tb);
end

endmodule

mux2x1_gate_level/mux.vcd
$date
	Mon Nov 07 19:37:33 2022
$end
$version
	ModelSim Version 2020.1
$end
$timescale
	1ps
$end

$scope module mux2x1_tb $end
$var reg 1 ! i0_tb $end
$var reg 1 " i1_tb $end
$var reg 1 # sel_tb $end
$var wire 1 $ y_tb $end

$scope module m1 $end
$var wire 1 % i0 $end
$var wire 1 & i1 $end
$var wire 1 ' sel $end
$var wire 1 $ y $end
$var wire 1 ( isel $end
$var wire 1 ) o1 $end
$var wire 1 * o2 $end
$upscope $end
$upscope $end
$enddefinitions $end
#0
$dumpvars
0!
1"
1#
1$
0(
0)
1*
1'
1&
0%
$end
#1
1!
1%
#2
0"
0&
0*
0$
#5
0!
1"
0#
0%
1&
0'
1(
#6
1!
1%
1)
1$
#7
0"
0&
#8
0!
1"
0%
1&
0)
0$
#9
1!
1#
1%
1'
1)
1*
0(
1$
0)
