full_adder_gate_level/fa.v
module fa (
    input   reg   a,    //Input a
    input   reg   b,    //Input b
    input   reg   cin,  //Input Carry
    output  wire  sum,  //Output Sum
    output  wire  cout  //Output Carry
    );
    
wire x1;    //output of xor1 gate connected to input of xor2 gate
wire a1;    //output of and1 gate connected to input of or1 gate
wire a2;    //output of and2 gate connected to input of or1 gate
wire a3;    //output of and3 gate connected to input of or1 gate


//Gate level Implementation for Sum output
xor xor1 (x1, a, b);
xor xor2 (sum, x1, cin);

//Gate level implementation for cout output
and and1 (a1,a,b);
and and2 (a2,a,cin);
and and3 (a3,b,cin);
or  or1  (cout, a1, a2, a3);

endmodule

full_adder_gate_level/fa_tb.v
`include "fa.v"     //include full added verilog file

module fa_tb;

    reg   a_tb;     //Input a
    reg   b_tb;     //Input b
    reg   cin_tb;   //Input Carry
    wire  sum_tb;   //Output Sum
    wire  cout_tb;  //Output Carry

//Instantiation of Full adder module
fa dut (.a(a_tb),
        .b(b_tb),
        .cin(cin_tb),
        .sum(sum_tb),
        .cout(cout_tb));


initial begin

    repeat (10) begin
        a_tb   = $random;
        b_tb   = $random;   
        cin_tb = $random;
        #1;
    end

end


initial begin
    $dumpfile("fa.vcd");
    $dumpvars(0,fa_tb);
end

initial begin
    $monitor("Time - %0t, a = %b, b = %b, cin = %b, sum = %b, cout = %b", $time, a_tb, b_tb, cin_tb, sum_tb, cout_tb);
end

endmodule

full_adder_gate_level/fa.vcd
$date
	Tue Nov 08 16:14:08 2022
$end
$version
	ModelSim Version 2020.1
$end
$timescale
	1ps
$end

$scope module fa_tb $end
$var reg 1 ! a_tb $end
$var reg 1 " b_tb $end
$var reg 1 # cin_tb $end
$var wire 1 $ sum_tb $end
$var wire 1 % cout_tb $end

$scope module dut $end
$var wire 1 & a $end
$var wire 1 ' b $end
$var wire 1 ( cin $end
$var wire 1 $ sum $end
$var wire 1 % cout $end
$var wire 1 ) x1 $end
$var wire 1 * a1 $end
$var wire 1 + a2 $end
$var wire 1 , a3 $end
$upscope $end
$upscope $end
$enddefinitions $end
#0
$dumpvars
0!
1"
1#
0$
1%
1)
0*
0+
1,
1(
1'
0&
$end
#1
1!
1&
1+
1*
0)
1$
#2
0"
0'
0,
0*
1)
0$
#5
0!
1"
0#
0&
1'
0(
0+
1$
0%
#6
1!
1&
1*
0)
1%
0$
#7
0"
0'
0*
1)
0%
1$
#8
0!
1"
0&
1'
#9
1!
1#
1&
1(
1+
1*
0)
1,
0$
1%
1$
