encoder8x3_decoder3x8/decoder3x8.v

/********************************************************************

Module          :   decoder8x3

Date            :   15 November, 2022

Author          :   Krunal Gandhi

Email           :   gkrunal72@gmail.com

History         :   1. 15 November, 2022 - Initial implementation

Summary         :   Implementation decoder8x3.

Inputs          :   i0_de, i1_de, i2_de

Outputs         :   o0_de, o1_de, o2_de, o3_de, o4_de, o5_de, o6_de, o7_de

Instantiation   :   N/A

********************************************************************/

module  decoder3x8 (
    output   wire        o0_de,
    output   wire        o1_de,
    output   wire        o2_de,
    output   wire        o3_de,
    output   wire        o4_de,
    output   wire        o5_de,
    output   wire        o6_de,
    output   wire        o7_de,
    input    wire       i0_de,
    input    wire       i1_de,
    input    wire       i2_de
);

and a1 (o0_de, ~i0_de, ~i1_de, ~i2_de);
and a2 (o1_de, i0_de, ~i1_de, ~i2_de);
and a3 (o2_de, ~i0_de, i1_de, ~i2_de);
and a4 (o3_de, i0_de, i1_de, ~i2_de);
and a5 (o4_de, ~i0_de, ~i1_de, i2_de);
and a6 (o5_de, i0_de, ~i1_de, i2_de);
and a7 (o6_de, ~i0_de, i1_de, i2_de);
and a8 (o7_de, i0_de, i1_de, i2_de);

endmodule

encoder8x3_decoder3x8/encoder8x3.v

/********************************************************************

Module          :   encoder8x3

Date            :   15 November, 2022

Author          :   Krunal Gandhi

Email           :   gkrunal72@gmail.com

History         :   1. 15 November, 2022 - Initial implementation

Summary         :   Implementation encoder8x3.

Inputs          :   i0_en, i1_en, i2_en, i3_en, i4_en, i5_en, i6_en, i7_en

Outputs         :   o0_en, o1_en, o2_en

Instantiation   :   N/A

********************************************************************/

module  encoder8x3 (
    input   wire        i0_en,
    input   wire        i1_en,
    input   wire        i2_en,
    input   wire        i3_en,
    input   wire        i4_en,
    input   wire        i5_en,
    input   wire        i6_en,
    input   wire        i7_en,
    output  wire         o0_en,
    output  wire         o1_en,
    output  wire         o2_en
);


or a1 (o2_en, i4_en, i5_en, i6_en, i7_en);
or a2 (o1_en, i2_en, i3_en, i6_en, i7_en);
or a3 (o0_en, i1_en, i3_en, i5_en, i7_en);

endmodule

encoder8x3_decoder3x8/encode_decode_tb.v

/********************************************************************

Module          :   encode_decode_tb

Date            :   15 November, 2022

Author          :   Krunal Gandhi

Email           :   gkrunal72@gmail.com

History         :   1. 15 November, 2022 - Initial implementation

Summary         :   Implementation encode_decode_tb.

Inputs          :   i0_de, i1_de, i2_de

Outputs         :   o0_de, o1_de, o2_de, o3_de, o4_de, o5_de, o6_de, o7_de

Instantiation   :   encoder8x3, decoder8x3

********************************************************************/

`include "encoder8x3.v"
`include "decoder3x8.v"

module encode_decode_tb;

//Inputs to Encoder 8x3
reg     i0_en_tb;
reg     i1_en_tb;
reg     i2_en_tb;
reg     i3_en_tb;
reg     i4_en_tb;
reg     i5_en_tb;
reg     i6_en_tb;
reg     i7_en_tb;

//Outputs of Encoder
wire    o0_en_tb;
wire    o1_en_tb;
wire    o2_en_tb;

//Outputs of Decoder 3x8
wire    o0_de_tb;
wire    o1_de_tb;
wire    o2_de_tb;
wire    o3_de_tb;
wire    o4_de_tb;
wire    o5_de_tb;
wire    o6_de_tb;
wire    o7_de_tb;

//Inputs of Decoder
wire    i0_de_tb;
wire    i1_de_tb;
wire    i2_de_tb;


//Instatiation
encoder8x3 en1 (
    .i0_en( i0_en_tb),          
    .i1_en( i1_en_tb),         
    .i2_en( i2_en_tb),        
    .i3_en( i3_en_tb),        
    .i4_en( i4_en_tb),        
    .i5_en( i5_en_tb),        
    .i6_en( i6_en_tb),        
    .i7_en( i7_en_tb),        
    .o0_en( o0_en_tb),       
    .o1_en( o1_en_tb),       
    .o2_en( o2_en_tb)
);

decoder3x8 de1 (
        .o0_de( o0_de_tb),
        .o1_de( o1_de_tb),
        .o2_de( o2_de_tb),
        .o3_de( o3_de_tb),
        .o4_de( o4_de_tb),
        .o5_de( o5_de_tb),
        .o6_de( o6_de_tb),
        .o7_de( o7_de_tb),
        .i0_de( o0_en_tb),
        .i1_de( o1_en_tb),
        .i2_de( o2_en_tb)
     );

initial begin
    repeat (10) begin
#1      i0_en_tb = 1;
        i1_en_tb = 0;
        i2_en_tb = 0;
        i3_en_tb = 0;
        i4_en_tb = 0;
        i5_en_tb = 0;
        i6_en_tb = 0;
        i7_en_tb = 0;

#1      i0_en_tb = 0;
        i1_en_tb = 1;
        i2_en_tb = 0;
        i3_en_tb = 0;
        i4_en_tb = 0;
        i5_en_tb = 0;
        i6_en_tb = 0;
        i7_en_tb = 0;
    
#1      i0_en_tb = 0;
        i1_en_tb = 0;
        i2_en_tb = 1;
        i3_en_tb = 0;
        i4_en_tb = 0;
        i5_en_tb = 0;
        i6_en_tb = 0;
        i7_en_tb = 0;

#1      i0_en_tb = 0;
        i1_en_tb = 0;
        i2_en_tb = 0;
        i3_en_tb = 1;
        i4_en_tb = 0;
        i5_en_tb = 0;
        i6_en_tb = 0;
        i7_en_tb = 0;

#1      i0_en_tb = 0;
        i1_en_tb = 0;
        i2_en_tb = 0;
        i3_en_tb = 0;
        i4_en_tb = 1;
        i5_en_tb = 0;
        i6_en_tb = 0;
        i7_en_tb = 0;

#1      i0_en_tb = 0;
        i1_en_tb = 0;
        i2_en_tb = 0;
        i3_en_tb = 0;
        i4_en_tb = 0;
        i5_en_tb = 1;
        i6_en_tb = 0;
        i7_en_tb = 0;

#1      i0_en_tb = 0;
        i1_en_tb = 0;
        i2_en_tb = 0;
        i3_en_tb = 0;
        i4_en_tb = 0;
        i5_en_tb = 0;
        i6_en_tb = 1;
        i7_en_tb = 0;

#1      i0_en_tb = 0;
        i1_en_tb = 0;
        i2_en_tb = 0;
        i3_en_tb = 0;
        i4_en_tb = 0;
        i5_en_tb = 0;
        i6_en_tb = 0;
        i7_en_tb = 1;
    end
end

initial begin

    $dumpfile("encode_decode.vcd");
    $dumpvars(0,encode_decode_tb);

end

initial begin

    $monitor("i0_en = %b, i1_en = %b, i2_en = %b, i3_en = %b, i4_en = %b, i5_en = %b, i6_en = %b, i7_en = %b", i0_en_tb, i1_en_tb, i2_en_tb, i3_en_tb, i4_en_tb, i5_en_tb, i6_en_tb, i7_en_tb);
    $monitor("o0_de = %b, o1_de = %b, o2_de = %b, o3_de = %b, o4_de = %b, o5_de = %b, o6_de = %b, o7_de = %b", o0_de_tb, o1_de_tb, o2_de_tb, o3_de_tb, o4_de_tb, o5_de_tb, o6_de_tb, o7_de_tb);

end

endmodule

encoder8x3_decoder3x8/encode_decode.vcd
$date
	Wed Nov 16 10:56:16 2022
$end
$version
	ModelSim Version 2020.1
$end
$timescale
	1ps
$end

$scope module encode_decode_tb $end
$var reg 1 ! i0_en_tb $end
$var reg 1 " i1_en_tb $end
$var reg 1 # i2_en_tb $end
$var reg 1 $ i3_en_tb $end
$var reg 1 % i4_en_tb $end
$var reg 1 & i5_en_tb $end
$var reg 1 ' i6_en_tb $end
$var reg 1 ( i7_en_tb $end
$var wire 1 ) o0_en_tb $end
$var wire 1 * o1_en_tb $end
$var wire 1 + o2_en_tb $end
$var wire 1 , o0_de_tb $end
$var wire 1 - o1_de_tb $end
$var wire 1 . o2_de_tb $end
$var wire 1 / o3_de_tb $end
$var wire 1 0 o4_de_tb $end
$var wire 1 1 o5_de_tb $end
$var wire 1 2 o6_de_tb $end
$var wire 1 3 o7_de_tb $end
$var wire 1 4 i0_de_tb $end
$var wire 1 5 i1_de_tb $end
$var wire 1 6 i2_de_tb $end

$scope module en1 $end
$var wire 1 7 i0_en $end
$var wire 1 8 i1_en $end
$var wire 1 9 i2_en $end
$var wire 1 : i3_en $end
$var wire 1 ; i4_en $end
$var wire 1 < i5_en $end
$var wire 1 = i6_en $end
$var wire 1 > i7_en $end
$var wire 1 ) o0_en $end
$var wire 1 * o1_en $end
$var wire 1 + o2_en $end
$upscope $end

$scope module de1 $end
$var wire 1 , o0_de $end
$var wire 1 - o1_de $end
$var wire 1 . o2_de $end
$var wire 1 / o3_de $end
$var wire 1 0 o4_de $end
$var wire 1 1 o5_de $end
$var wire 1 2 o6_de $end
$var wire 1 3 o7_de $end
$var wire 1 ) i0_de $end
$var wire 1 * i1_de $end
$var wire 1 + i2_de $end
$upscope $end
$upscope $end
$enddefinitions $end
#0
$dumpvars
x!
x"
x#
x$
x%
x&
x'
x(
x)
x*
x+
x,
x-
x.
x/
x0
x1
x2
x3
z4
z5
z6
x>
x=
x<
x;
x:
x9
x8
x7
$end
#1
1!
0"
0#
0$
0%
0&
0'
0(
17
08
09
0:
0;
0<
0=
0>
0)
0*
0+
03
01
0/
0-
02
0.
00
1,
#2
0!
1"
07
18
1)
1-
0,
#3
0"
1#
08
19
0)
1*
0-
1.
#4
0#
1$
09
1:
1)
1/
0.
#5
0$
1%
0:
1;
0)
0*
1+
0/
10
#6
0%
1&
0;
1<
1)
11
00
#7
0&
1'
0<
1=
0)
1*
01
12
#8
0'
1(
0=
1>
1)
13
02
#9
1!
0(
17
0>
0)
0*
0+
03
1,
#10
0!
1"
07
18
1)
1-
0,
#11
0"
1#
08
19
0)
1*
0-
1.
#12
0#
1$
09
1:
1)
1/
0.
#13
0$
1%
0:
1;
0)
0*
1+
0/
10
#14
0%
1&
0;
1<
1)
11
00
#15
0&
1'
0<
1=
0)
1*
01
12
#16
0'
1(
0=
1>
1)
13
02
#17
1!
0(
17
0>
0)
0*
0+
03
1,
#18
0!
1"
07
18
1)
1-
0,
#19
0"
1#
08
19
0)
1*
0-
1.
#20
0#
1$
09
1:
1)
1/
0.
#21
0$
1%
0:
1;
0)
0*
1+
0/
10
#22
0%
1&
0;
1<
1)
11
00
#23
0&
1'
0<
1=
0)
1*
01
12
#24
0'
1(
0=
1>
1)
13
02
#25
1!
0(
17
0>
0)
0*
0+
03
1,
#26
0!
1"
07
18
1)
1-
0,
#27
0"
1#
08
19
0)
1*
0-
1.
#28
0#
1$
09
1:
1)
1/
0.
#29
0$
1%
0:
1;
0)
0*
1+
0/
10
#30
0%
1&
0;
1<
1)
11
00
#31
0&
1'
0<
1=
0)
1*
01
12
#32
0'
1(
0=
1>
1)
13
02
#33
1!
0(
17
0>
0)
0*
0+
03
1,
#34
0!
1"
07
18
1)
1-
0,
#35
0"
1#
08
19
0)
1*
0-
1.
#36
0#
1$
09
1:
1)
1/
0.
#37
0$
1%
0:
1;
0)
0*
1+
0/
10
#38
0%
1&
0;
1<
1)
11
00
#39
0&
1'
0<
1=
0)
1*
01
12
#40
0'
1(
0=
1>
1)
13
02
#41
1!
0(
17
0>
0)
0*
0+
03
1,
#42
0!
1"
07
18
1)
1-
0,
#43
0"
1#
08
19
0)
1*
0-
1.
#44
0#
1$
09
1:
1)
1/
0.
#45
0$
1%
0:
1;
0)
0*
1+
0/
10
#46
0%
1&
0;
1<
1)
11
00
#47
0&
1'
0<
1=
0)
1*
01
12
#48
0'
1(
0=
1>
1)
13
02
#49
1!
0(
17
0>
0)
0*
0+
03
1,
#50
0!
1"
07
18
1)
1-
0,
#51
0"
1#
08
19
0)
1*
0-
1.
#52
0#
1$
09
1:
1)
1/
0.
#53
0$
1%
0:
1;
0)
0*
1+
0/
10
#54
0%
1&
0;
1<
1)
11
00
#55
0&
1'
0<
1=
0)
1*
01
12
#56
0'
1(
0=
1>
1)
13
02
#57
1!
0(
17
0>
0)
0*
0+
03
1,
#58
0!
1"
07
18
1)
1-
0,
#59
0"
1#
08
19
0)
1*
0-
1.
#60
0#
1$
09
1:
1)
1/
0.
#61
0$
1%
0:
1;
0)
0*
1+
0/
10
#62
0%
1&
0;
1<
1)
11
00
#63
0&
1'
0<
1=
0)
1*
01
12
#64
0'
1(
0=
1>
1)
13
02
#65
1!
0(
17
0>
0)
0*
0+
03
1,
#66
0!
1"
07
18
1)
1-
0,
#67
0"
1#
08
19
0)
1*
0-
1.
#68
0#
1$
09
1:
1)
1/
0.
#69
0$
1%
0:
1;
0)
0*
1+
0/
10
#70
0%
1&
0;
1<
1)
11
00
#71
0&
1'
0<
1=
0)
1*
01
12
#72
0'
1(
0=
1>
1)
13
02
#73
1!
0(
17
0>
0)
0*
0+
03
1,
#74
0!
1"
07
18
1)
1-
0,
#75
0"
1#
08
19
0)
1*
0-
1.
#76
0#
1$
09
1:
1)
1/
0.
#77
0$
1%
0:
1;
0)
0*
1+
0/
10
#78
0%
1&
0;
1<
1)
11
00
#79
0&
1'
0<
1=
0)
1*
01
12
#80
0'
1(
0=
1>
1)
13
02
