counter/counter_1bit.v
/********************************************************************

Module          :   counter_1bit

Date            :   1 December, 2022

Author          :   Krunal Gandhi

Email           :   gkrunal72@gmail.com

History         :   1. 1 December, 2022 - Initial implementation

Summary         :   Implementation of 1 bit counter.

Inputs          :   clk, rst

Outputs         :   count

Instantiation   :   N/A

********************************************************************/

module counter_1bit 
    #(parameter N = 4)
    (
    input   wire         clk,
    input   wire         rst,
    output  reg  [N-1:0] count
);

always @(posedge clk, posedge rst) begin
    
    if(rst == 1)
        count <= 0;
    else
        count <= count + 1'b1;

end

endmodule

counter/counter_1bit_tb.v
/********************************************************************

Module          :   counter_1bit_tb

Date            :   1 December, 2022

Author          :   Krunal Gandhi

Email           :   gkrunal72@gmail.com

History         :   1. 1 December, 2022 - Initial implementation

Summary         :   Implementation of testbench for 1 bit counter.

Inputs          :   clk, rst

Outputs         :   count

Instantiation   :   counter_1bit

********************************************************************/
`include "counter_1bit.v"

module counter_1bit_tb
    #(parameter N= 4);
    reg          clk;
    reg          rst;
    wire [N-1:0] count;

counter_1bit dut (
    .clk(clk),
    .rst(rst),
    .count(count)
);

initial begin
    clk <= 1'b0;
    
    repeat (100)
        #5 rst <= $random;
end

initial begin
    repeat (500)
        #1 clk <= ~clk;
end


initial begin

    $dumpfile("counter_1bit.vcd");
    $dumpvars(0,counter_1bit_tb);

end


initial begin

    $monitor("time = %0t, rst = %b, count = %d",$time, rst, count);

end

endmodule

counter/counter_1bit.vcd
$date
	Thu Dec 01 16:26:19 2022
$end
$version
	ModelSim Version 2020.1
$end
$timescale
	1ps
$end

$scope module counter_1bit_tb $end
$var parameter 32 ! N $end
$var reg 1 " clk $end
$var reg 1 # rst $end
$var wire 1 $ count [3] $end
$var wire 1 % count [2] $end
$var wire 1 & count [1] $end
$var wire 1 ' count [0] $end

$scope module dut $end
$var parameter 32 ( N $end
$var wire 1 ) clk $end
$var wire 1 * rst $end
$var reg 4 + count [3:0] $end
$upscope $end
$upscope $end
$enddefinitions $end
#0
$dumpvars
0"
x#
bx +
b100 !
b100 (
x'
x&
x%
x$
x*
0)
$end
#1
1"
1)
#2
0"
0)
#3
1"
1)
#4
0"
0)
#5
0#
1"
0*
1)
#6
0"
0)
#7
1"
1)
#8
0"
0)
#9
1"
1)
#10
1#
0"
1*
0)
b0 +
0'
0&
0%
0$
#11
1"
1)
#12
0"
0)
#13
1"
1)
#14
0"
0)
#15
1"
1)
#16
0"
0)
#17
1"
1)
#18
0"
0)
#19
1"
1)
#20
0"
0)
#21
1"
1)
#22
0"
0)
#23
1"
1)
#24
0"
0)
#25
1"
1)
#26
0"
0)
#27
1"
1)
#28
0"
0)
#29
1"
1)
#30
0"
0)
#31
1"
1)
#32
0"
0)
#33
1"
1)
#34
0"
0)
#35
1"
1)
#36
0"
0)
#37
1"
1)
#38
0"
0)
#39
1"
1)
#40
0#
0"
0*
0)
#41
1"
1)
b1 +
1'
#42
0"
0)
#43
1"
1)
b10 +
0'
1&
#44
0"
0)
#45
1#
1"
1*
1)
b0 +
0&
#46
0"
0)
#47
1"
1)
#48
0"
0)
#49
1"
1)
#50
0"
0)
#51
1"
1)
#52
0"
0)
#53
1"
1)
#54
0"
0)
#55
0#
1"
0*
1)
b1 +
1'
#56
0"
0)
#57
1"
1)
b10 +
0'
1&
#58
0"
0)
#59
1"
1)
b11 +
1'
#60
1#
0"
1*
0)
b0 +
0'
0&
#61
1"
1)
#62
0"
0)
#63
1"
1)
#64
0"
0)
#65
1"
1)
#66
0"
0)
#67
1"
1)
#68
0"
0)
#69
1"
1)
#70
0#
0"
0*
0)
#71
1"
1)
b1 +
1'
#72
0"
0)
#73
1"
1)
b10 +
0'
1&
#74
0"
0)
#75
1#
1"
1*
1)
b0 +
0&
#76
0"
0)
#77
1"
1)
#78
0"
0)
#79
1"
1)
#80
0#
0"
0*
0)
#81
1"
1)
b1 +
1'
#82
0"
0)
#83
1"
1)
b10 +
0'
1&
#84
0"
0)
#85
1#
1"
1*
1)
b0 +
0&
#86
0"
0)
#87
1"
1)
#88
0"
0)
#89
1"
1)
#90
0#
0"
0*
0)
#91
1"
1)
b1 +
1'
#92
0"
0)
#93
1"
1)
b10 +
0'
1&
#94
0"
0)
#95
1#
1"
1*
1)
b0 +
0&
#96
0"
0)
#97
1"
1)
#98
0"
0)
#99
1"
1)
#100
0"
0)
#101
1"
1)
#102
0"
0)
#103
1"
1)
#104
0"
0)
#105
0#
1"
0*
1)
b1 +
1'
#106
0"
0)
#107
1"
1)
b10 +
0'
1&
#108
0"
0)
#109
1"
1)
b11 +
1'
#110
1#
0"
1*
0)
b0 +
0'
0&
#111
1"
1)
#112
0"
0)
#113
1"
1)
#114
0"
0)
#115
0#
1"
0*
1)
b1 +
1'
#116
0"
0)
#117
1"
1)
b10 +
0'
1&
#118
0"
0)
#119
1"
1)
b11 +
1'
#120
0"
0)
#121
1"
1)
b100 +
0'
0&
1%
#122
0"
0)
#123
1"
1)
b101 +
1'
#124
0"
0)
#125
1"
1)
b110 +
0'
1&
#126
0"
0)
#127
1"
1)
b111 +
1'
#128
0"
0)
#129
1"
1)
b1000 +
0'
0&
0%
1$
#130
1#
0"
1*
0)
b0 +
0$
#131
1"
1)
#132
0"
0)
#133
1"
1)
#134
0"
0)
#135
0#
1"
0*
1)
b1 +
1'
#136
0"
0)
#137
1"
1)
b10 +
0'
1&
#138
0"
0)
#139
1"
1)
b11 +
1'
#140
1#
0"
1*
0)
b0 +
0'
0&
#141
1"
1)
#142
0"
0)
#143
1"
1)
#144
0"
0)
#145
1"
1)
#146
0"
0)
#147
1"
1)
#148
0"
0)
#149
1"
1)
#150
0"
0)
#151
1"
1)
#152
0"
0)
#153
1"
1)
#154
0"
0)
#155
1"
1)
#156
0"
0)
#157
1"
1)
#158
0"
0)
#159
1"
1)
#160
0#
0"
0*
0)
#161
1"
1)
b1 +
1'
#162
0"
0)
#163
1"
1)
b10 +
0'
1&
#164
0"
0)
#165
1"
1)
b11 +
1'
#166
0"
0)
#167
1"
1)
b100 +
0'
0&
1%
#168
0"
0)
#169
1"
1)
b101 +
1'
#170
0"
0)
#171
1"
1)
b110 +
0'
1&
#172
0"
0)
#173
1"
1)
b111 +
1'
#174
0"
0)
#175
1"
1)
b1000 +
0'
0&
0%
1$
#176
0"
0)
#177
1"
1)
b1001 +
1'
#178
0"
0)
#179
1"
1)
b1010 +
0'
1&
#180
1#
0"
1*
0)
b0 +
0&
0$
#181
1"
1)
#182
0"
0)
#183
1"
1)
#184
0"
0)
#185
0#
1"
0*
1)
b1 +
1'
#186
0"
0)
#187
1"
1)
b10 +
0'
1&
#188
0"
0)
#189
1"
1)
b11 +
1'
#190
1#
0"
1*
0)
b0 +
0'
0&
#191
1"
1)
#192
0"
0)
#193
1"
1)
#194
0"
0)
#195
1"
1)
#196
0"
0)
#197
1"
1)
#198
0"
0)
#199
1"
1)
#200
0"
0)
#201
1"
1)
#202
0"
0)
#203
1"
1)
#204
0"
0)
#205
1"
1)
#206
0"
0)
#207
1"
1)
#208
0"
0)
#209
1"
1)
#210
0"
0)
#211
1"
1)
#212
0"
0)
#213
1"
1)
#214
0"
0)
#215
0#
1"
0*
1)
b1 +
1'
#216
0"
0)
#217
1"
1)
b10 +
0'
1&
#218
0"
0)
#219
1"
1)
b11 +
1'
#220
0"
0)
#221
1"
1)
b100 +
0'
0&
1%
#222
0"
0)
#223
1"
1)
b101 +
1'
#224
0"
0)
#225
1#
1"
1*
1)
b0 +
0'
0%
#226
0"
0)
#227
1"
1)
#228
0"
0)
#229
1"
1)
#230
0"
0)
#231
1"
1)
#232
0"
0)
#233
1"
1)
#234
0"
0)
#235
1"
1)
#236
0"
0)
#237
1"
1)
#238
0"
0)
#239
1"
1)
#240
0#
0"
0*
0)
#241
1"
1)
b1 +
1'
#242
0"
0)
#243
1"
1)
b10 +
0'
1&
#244
0"
0)
#245
1"
1)
b11 +
1'
#246
0"
0)
#247
1"
1)
b100 +
0'
0&
1%
#248
0"
0)
#249
1"
1)
b101 +
1'
#250
0"
0)
#251
1"
1)
b110 +
0'
1&
#252
0"
0)
#253
1"
1)
b111 +
1'
#254
0"
0)
#255
1"
1)
b1000 +
0'
0&
0%
1$
#256
0"
0)
#257
1"
1)
b1001 +
1'
#258
0"
0)
#259
1"
1)
b1010 +
0'
1&
#260
0"
0)
#261
1"
1)
b1011 +
1'
#262
0"
0)
#263
1"
1)
b1100 +
0'
0&
1%
#264
0"
0)
#265
1#
1"
1*
1)
b0 +
0%
0$
#266
0"
0)
#267
1"
1)
#268
0"
0)
#269
1"
1)
#270
0#
0"
0*
0)
#271
1"
1)
b1 +
1'
#272
0"
0)
#273
1"
1)
b10 +
0'
1&
#274
0"
0)
#275
1"
1)
b11 +
1'
#276
0"
0)
#277
1"
1)
b100 +
0'
0&
1%
#278
0"
0)
#279
1"
1)
b101 +
1'
#280
1#
0"
1*
0)
b0 +
0'
0%
#281
1"
1)
#282
0"
0)
#283
1"
1)
#284
0"
0)
#285
1"
1)
#286
0"
0)
#287
1"
1)
#288
0"
0)
#289
1"
1)
#290
0#
0"
0*
0)
#291
1"
1)
b1 +
1'
#292
0"
0)
#293
1"
1)
b10 +
0'
1&
#294
0"
0)
#295
1"
1)
b11 +
1'
#296
0"
0)
#297
1"
1)
b100 +
0'
0&
1%
#298
0"
0)
#299
1"
1)
b101 +
1'
#300
0"
0)
#301
1"
1)
b110 +
0'
1&
#302
0"
0)
#303
1"
1)
b111 +
1'
#304
0"
0)
#305
1"
1)
b1000 +
0'
0&
0%
1$
#306
0"
0)
#307
1"
1)
b1001 +
1'
#308
0"
0)
#309
1"
1)
b1010 +
0'
1&
#310
0"
0)
#311
1"
1)
b1011 +
1'
#312
0"
0)
#313
1"
1)
b1100 +
0'
0&
1%
#314
0"
0)
#315
1#
1"
1*
1)
b0 +
0%
0$
#316
0"
0)
#317
1"
1)
#318
0"
0)
#319
1"
1)
#320
0"
0)
#321
1"
1)
#322
0"
0)
#323
1"
1)
#324
0"
0)
#325
1"
1)
#326
0"
0)
#327
1"
1)
#328
0"
0)
#329
1"
1)
#330
0"
0)
#331
1"
1)
#332
0"
0)
#333
1"
1)
#334
0"
0)
#335
1"
1)
#336
0"
0)
#337
1"
1)
#338
0"
0)
#339
1"
1)
#340
0#
0"
0*
0)
#341
1"
1)
b1 +
1'
#342
0"
0)
#343
1"
1)
b10 +
0'
1&
#344
0"
0)
#345
1"
1)
b11 +
1'
#346
0"
0)
#347
1"
1)
b100 +
0'
0&
1%
#348
0"
0)
#349
1"
1)
b101 +
1'
#350
1#
0"
1*
0)
b0 +
0'
0%
#351
1"
1)
#352
0"
0)
#353
1"
1)
#354
0"
0)
#355
1"
1)
#356
0"
0)
#357
1"
1)
#358
0"
0)
#359
1"
1)
#360
0"
0)
#361
1"
1)
#362
0"
0)
#363
1"
1)
#364
0"
0)
#365
0#
1"
0*
1)
b1 +
1'
#366
0"
0)
#367
1"
1)
b10 +
0'
1&
#368
0"
0)
#369
1"
1)
b11 +
1'
#370
0"
0)
#371
1"
1)
b100 +
0'
0&
1%
#372
0"
0)
#373
1"
1)
b101 +
1'
#374
0"
0)
#375
1#
1"
1*
1)
b0 +
0'
0%
#376
0"
0)
#377
1"
1)
#378
0"
0)
#379
1"
1)
#380
0"
0)
#381
1"
1)
#382
0"
0)
#383
1"
1)
#384
0"
0)
#385
0#
1"
0*
1)
b1 +
1'
#386
0"
0)
#387
1"
1)
b10 +
0'
1&
#388
0"
0)
#389
1"
1)
b11 +
1'
#390
1#
0"
1*
0)
b0 +
0'
0&
#391
1"
1)
#392
0"
0)
#393
1"
1)
#394
0"
0)
#395
1"
1)
#396
0"
0)
#397
1"
1)
#398
0"
0)
#399
1"
1)
#400
0#
0"
0*
0)
#401
1"
1)
b1 +
1'
#402
0"
0)
#403
1"
1)
b10 +
0'
1&
#404
0"
0)
#405
1#
1"
1*
1)
b0 +
0&
#406
0"
0)
#407
1"
1)
#408
0"
0)
#409
1"
1)
#410
0"
0)
#411
1"
1)
#412
0"
0)
#413
1"
1)
#414
0"
0)
#415
1"
1)
#416
0"
0)
#417
1"
1)
#418
0"
0)
#419
1"
1)
#420
0#
0"
0*
0)
#421
1"
1)
b1 +
1'
#422
0"
0)
#423
1"
1)
b10 +
0'
1&
#424
0"
0)
#425
1#
1"
1*
1)
b0 +
0&
#426
0"
0)
#427
1"
1)
#428
0"
0)
#429
1"
1)
#430
0"
0)
#431
1"
1)
#432
0"
0)
#433
1"
1)
#434
0"
0)
#435
0#
1"
0*
1)
b1 +
1'
#436
0"
0)
#437
1"
1)
b10 +
0'
1&
#438
0"
0)
#439
1"
1)
b11 +
1'
#440
0"
0)
#441
1"
1)
b100 +
0'
0&
1%
#442
0"
0)
#443
1"
1)
b101 +
1'
#444
0"
0)
#445
1"
1)
b110 +
0'
1&
#446
0"
0)
#447
1"
1)
b111 +
1'
#448
0"
0)
#449
1"
1)
b1000 +
0'
0&
0%
1$
#450
0"
0)
#451
1"
1)
b1001 +
1'
#452
0"
0)
#453
1"
1)
b1010 +
0'
1&
#454
0"
0)
#455
1#
1"
1*
1)
b0 +
0&
0$
#456
0"
0)
#457
1"
1)
#458
0"
0)
#459
1"
1)
#460
0"
0)
#461
1"
1)
#462
0"
0)
#463
1"
1)
#464
0"
0)
#465
0#
1"
0*
1)
b1 +
1'
#466
0"
0)
#467
1"
1)
b10 +
0'
1&
#468
0"
0)
#469
1"
1)
b11 +
1'
#470
0"
0)
#471
1"
1)
b100 +
0'
0&
1%
#472
0"
0)
#473
1"
1)
b101 +
1'
#474
0"
0)
#475
1#
1"
1*
1)
b0 +
0'
0%
#476
0"
0)
#477
1"
1)
#478
0"
0)
#479
1"
1)
#480
0"
0)
#481
1"
1)
#482
0"
0)
#483
1"
1)
#484
0"
0)
#485
1"
1)
#486
0"
0)
#487
1"
1)
#488
0"
0)
#489
1"
1)
#490
0"
0)
#491
1"
1)
#492
0"
0)
#493
1"
1)
#494
0"
0)
#495
1"
1)
#496
0"
0)
#497
1"
1)
#498
0"
0)
#499
1"
1)
#500
0#
0"
0*
0)
