mux4x1_assign/mux4x1.v

/********************************************************************

Module          :   mux4x1

Date            :   10 November, 2022

Author          :   Krunal Gandhi

Email           :   gkrunal72@gmail.com

History         :   1. 10 November, 2022 - Initial implementation

Summary         :   Implementation of Mux4x1 using assign statements.
                    core logic is of mux4x1 using mux2x1.

Inputs          :   i0, i1, i2, i3, sel

Outputs         :   Out

Instantiation   :   N/A

********************************************************************/

module mux4x1 (
    input   wire        i0,
    input   wire        i1,
    input   wire        i2,
    input   wire        i3,
    input   wire  [1:0] sel,
    output  reg         out
    );

wire    m1;
wire    m2;

assign m1 = sel[0] ? i1 : i0;
assign m2 = sel[0] ? i3 : i2;
assign out = sel[1] ? m2 : m1;

endmodule

mux4x1_assign/mux4x1_tb.v
/********************************************************************

Module          :   mux4x1_tb

Date            :   10 November, 2022

Author          :   Krunal Gandhi

Email           :   gkrunal72@gmail.com

History         :   1. 10 November, 2022 - Initial implementation

Summary         :   Test bench for mux4x1.v implemented using assign statements

Inputs          :   i0_tb, i1_tb, i2_tb, i3_tb, sel_tb

Outputs         :   Out_tb

Instantiation   :   mux4x1

********************************************************************/

`include "mux4x1.v"

module mux4x1_tb;

//Outputs
reg         i0_tb;
reg         i1_tb;
reg         i2_tb;
reg         i3_tb;
reg  [1:0]  sel_tb;

//Input
wire        out_tb;

//Instantiation
mux4x1 dut (.i0(i0_tb),
            .i1(i1_tb),
            .i2(i2_tb),
            .i3(i3_tb),
            .sel(sel_tb),
            .out(out_tb));


initial begin
    repeat (20) begin
        i0_tb = $random;
        i1_tb = $random;
        i2_tb = $random;
        i3_tb = $random;
        sel_tb = $random;
        #1;
    end
end

initial begin
    $dumpfile("mux4x1.vcd");
    $dumpvars(0,mux4x1_tb);
end


initial begin
    $monitor("Time = %0t, I0 = %b, I1 = %b, I2 = %b, I3 = %b, SEL = %d, Out = %b", $time, i0_tb, i1_tb, i2_tb, i3_tb, sel_tb, out_tb);
end

endmodule

mux4x1_assign/mux4x1.vcd
$date
	Thu Nov 10 16:53:47 2022
$end
$version
	ModelSim Version 2020.1
$end
$timescale
	1ps
$end

$scope module mux4x1_tb $end
$var reg 1 ! i0_tb $end
$var reg 1 " i1_tb $end
$var reg 1 # i2_tb $end
$var reg 1 $ i3_tb $end
$var reg 2 % sel_tb [1:0] $end
$var wire 1 & out_tb $end

$scope module dut $end
$var wire 1 ' i0 $end
$var wire 1 ( i1 $end
$var wire 1 ) i2 $end
$var wire 1 * i3 $end
$var wire 1 + sel [1] $end
$var wire 1 , sel [0] $end
$var reg 1 - out $end
$var wire 1 . m1 $end
$var wire 1 / m2 $end
$upscope $end
$upscope $end
$enddefinitions $end
#0
$dumpvars
0!
1"
1#
1$
b1 %
1-
1&
1.
1/
1,
0+
1*
1)
1(
0'
$end
#1
1!
0#
1'
0)
#2
0!
1#
0$
0'
1)
0*
0/
#3
0#
1$
b11 %
0)
1*
1+
1/
#4
0$
b0 %
0*
0,
0+
0.
0/
0-
0&
#5
1!
0"
1#
1$
b1 %
1'
0(
1)
1*
1,
1/
#6
0#
0$
b10 %
0)
0*
0,
1+
1.
0/
#7
1#
1$
b11 %
1)
1*
1,
0.
1/
1-
1&
#8
1"
0#
0$
b1 %
1(
0)
0*
0+
0/
1.
#9
b0 %
0,
#10
0!
0"
1#
0'
0(
1)
1/
0.
0-
0&
#11
1!
1"
0#
b10 %
1'
1(
0)
1+
0/
1.
#12
0!
0"
1#
1$
b1 %
0'
0(
1)
1*
1,
0+
1/
0.
#13
1!
1"
0#
0$
1'
1(
0)
0*
0/
1.
1-
1&
#14
b11 %
1+
0-
0&
#15
0"
1#
1$
b0 %
0(
1)
1*
0,
0+
1/
1-
1&
#16
1"
0$
b11 %
1(
0*
1,
1+
0/
0-
0&
#17
0"
0#
b0 %
0(
0)
0,
0+
1-
1&
#18
1"
b1 %
1(
1,
#19
1#
1$
b0 %
1)
1*
0,
1/
